bower_cache-0.5.0.dist-info/RECORD
bower_cache-0.5.0.dist-info/DESCRIPTION.rst
bower_cache-0.5.0.dist-info/metadata.json
bower_cache-0.5.0.dist-info/WHEEL
bower_cache-0.5.0.dist-info/METADATA
bower_cache-0.5.0.dist-info/top_level.txt
bower_cache-0.5.0.dist-info/entry_points.txt
bowercache/_compat.py
bowercache/init.py
bowercache/__init__.py
bowercache/project_template/manage.py
bowercache/project_template/project_name/urls.py
bowercache/project_template/project_name/settings.py
bowercache/project_template/project_name/wsgi.py
bowercache/project_template/project_name/celery.py
bowercache/project_template/project_name/__init__.py
