Metadata-Version: 2.0
Name: bower-cache
Version: 0.5.0
Summary: A local caching proxy for Bower packages.
Home-page: https://github.com/tinche/bower-cache
Author: Tin Tvrtkovic
Author-email: tinchester@gmail.com
License: MIT
Keywords: bower
Platform: UNKNOWN
Classifier: Development Status :: 3 - Alpha
Classifier: Framework :: Django
Classifier: Intended Audience :: System Administrators
Classifier: License :: OSI Approved :: MIT License
Classifier: Natural Language :: English
Classifier: Programming Language :: Python :: 2
Classifier: Programming Language :: Python :: 2.6
Classifier: Programming Language :: Python :: 2.7
Classifier: Programming Language :: Python :: 3.3
Classifier: Programming Language :: Python :: 3.4
Classifier: Programming Language :: Python :: Implementation :: PyPy
Requires-Dist: django-bower-cache (==0.5.0)
Requires-Dist: django-celery (==3.1.16)
Requires-Dist: dj-static (==0.0.6)
Requires-Dist: gunicorn (==19.3.0)
Requires-Dist: importlib; python_version=="2.6"
